[
    {
        "name": "current_weather",
        "qualifiedName": "current_weather",
        "href": "current_weather/current_weather-library.html",
        "type": "library",
        "overriddenDepth": 0,
        "packageName": "weather"
    },
    {
        "name": "Clouds",
        "qualifiedName": "current_weather.Clouds",
        "href": "current_weather/Clouds-class.html",
        "type": "class",
        "overriddenDepth": 0,
        "packageName": "weather",
        "enclosedBy": {
            "name": "current_weather",
            "type": "library"
        }
    },
    {
        "name": "operator ==",
        "qualifiedName": "current_weather.Clouds.==",
        "href": "current_weather/Clouds/operator_equals.html",
        "type": "method",
        "overriddenDepth": 1,
        "packageName": "weather",
        "enclosedBy": {
            "name": "Clouds",
            "type": "class"
        }
    },
    {
        "name": "Clouds",
        "qualifiedName": "current_weather.Clouds.Clouds",
        "href": "current_weather/Clouds/Clouds.html",
        "type": "constructor",
        "overriddenDepth": 0,
        "packageName": "weather",
        "enclosedBy": {
            "name": "Clouds",
            "type": "class"
        }
    },
    {
        "name": "copyWith",
        "qualifiedName": "current_weather.Clouds.copyWith",
        "href": "current_weather/Clouds/copyWith.html",
        "type": "method",
        "overriddenDepth": 0,
        "packageName": "weather",
        "enclosedBy": {
            "name": "Clouds",
            "type": "class"
        }
    },
    {
        "name": "Clouds.fromJson",
        "qualifiedName": "current_weather.Clouds.fromJson",
        "href": "current_weather/Clouds/Clouds.fromJson.html",
        "type": "constructor",
        "overriddenDepth": 0,
        "packageName": "weather",
        "enclosedBy": {
            "name": "Clouds",
            "type": "class"
        }
    },
    {
        "name": "Clouds.fromMap",
        "qualifiedName": "current_weather.Clouds.fromMap",
        "href": "current_weather/Clouds/Clouds.fromMap.html",
        "type": "constructor",
        "overriddenDepth": 0,
        "packageName": "weather",
        "enclosedBy": {
            "name": "Clouds",
            "type": "class"
        }
    },
    {
        "name": "hashCode",
        "qualifiedName": "current_weather.Clouds.hashCode",
        "href": "current_weather/Clouds/hashCode.html",
        "type": "property",
        "overriddenDepth": 0,
        "packageName": "weather",
        "enclosedBy": {
            "name": "Clouds",
            "type": "class"
        }
    },
    {
        "name": "name",
        "qualifiedName": "current_weather.Clouds.name",
        "href": "current_weather/Clouds/name.html",
        "type": "property",
        "overriddenDepth": 0,
        "packageName": "weather",
        "enclosedBy": {
            "name": "Clouds",
            "type": "class"
        }
    },
    {
        "name": "toJson",
        "qualifiedName": "current_weather.Clouds.toJson",
        "href": "current_weather/Clouds/toJson.html",
        "type": "method",
        "overriddenDepth": 0,
        "packageName": "weather",
        "enclosedBy": {
            "name": "Clouds",
            "type": "class"
        }
    },
    {
        "name": "toMap",
        "qualifiedName": "current_weather.Clouds.toMap",
        "href": "current_weather/Clouds/toMap.html",
        "type": "method",
        "overriddenDepth": 0,
        "packageName": "weather",
        "enclosedBy": {
            "name": "Clouds",
            "type": "class"
        }
    },
    {
        "name": "toString",
        "qualifiedName": "current_weather.Clouds.toString",
        "href": "current_weather/Clouds/toString.html",
        "type": "method",
        "overriddenDepth": 1,
        "packageName": "weather",
        "enclosedBy": {
            "name": "Clouds",
            "type": "class"
        }
    },
    {
        "name": "value",
        "qualifiedName": "current_weather.Clouds.value",
        "href": "current_weather/Clouds/value.html",
        "type": "property",
        "overriddenDepth": 0,
        "packageName": "weather",
        "enclosedBy": {
            "name": "Clouds",
            "type": "class"
        }
    },
    {
        "name": "Condition",
        "qualifiedName": "current_weather.Condition",
        "href": "current_weather/Condition-class.html",
        "type": "class",
        "overriddenDepth": 0,
        "packageName": "weather",
        "enclosedBy": {
            "name": "current_weather",
            "type": "library"
        }
    },
    {
        "name": "Condition",
        "qualifiedName": "current_weather.Condition.Condition",
        "href": "current_weather/Condition/Condition.html",
        "type": "constructor",
        "overriddenDepth": 0,
        "packageName": "weather",
        "enclosedBy": {
            "name": "Condition",
            "type": "class"
        }
    },
    {
        "name": "code",
        "qualifiedName": "current_weather.Condition.code",
        "href": "current_weather/Condition/code.html",
        "type": "property",
        "overriddenDepth": 0,
        "packageName": "weather",
        "enclosedBy": {
            "name": "Condition",
            "type": "class"
        }
    },
    {
        "name": "condition",
        "qualifiedName": "current_weather.Condition.condition",
        "href": "current_weather/Condition/condition.html",
        "type": "property",
        "overriddenDepth": 0,
        "packageName": "weather",
        "enclosedBy": {
            "name": "Condition",
            "type": "class"
        }
    },
    {
        "name": "Condition.fromJson",
        "qualifiedName": "current_weather.Condition.fromJson",
        "href": "current_weather/Condition/Condition.fromJson.html",
        "type": "constructor",
        "overriddenDepth": 0,
        "packageName": "weather",
        "enclosedBy": {
            "name": "Condition",
            "type": "class"
        }
    },
    {
        "name": "Condition.fromMap",
        "qualifiedName": "current_weather.Condition.fromMap",
        "href": "current_weather/Condition/Condition.fromMap.html",
        "type": "constructor",
        "overriddenDepth": 0,
        "packageName": "weather",
        "enclosedBy": {
            "name": "Condition",
            "type": "class"
        }
    },
    {
        "name": "toJson",
        "qualifiedName": "current_weather.Condition.toJson",
        "href": "current_weather/Condition/toJson.html",
        "type": "method",
        "overriddenDepth": 0,
        "packageName": "weather",
        "enclosedBy": {
            "name": "Condition",
            "type": "class"
        }
    },
    {
        "name": "toMap",
        "qualifiedName": "current_weather.Condition.toMap",
        "href": "current_weather/Condition/toMap.html",
        "type": "method",
        "overriddenDepth": 0,
        "packageName": "weather",
        "enclosedBy": {
            "name": "Condition",
            "type": "class"
        }
    },
    {
        "name": "Coordinates",
        "qualifiedName": "current_weather.Coordinates",
        "href": "current_weather/Coordinates-class.html",
        "type": "class",
        "overriddenDepth": 0,
        "packageName": "weather",
        "enclosedBy": {
            "name": "current_weather",
            "type": "library"
        }
    },
    {
        "name": "operator ==",
        "qualifiedName": "current_weather.Coordinates.==",
        "href": "current_weather/Coordinates/operator_equals.html",
        "type": "method",
        "overriddenDepth": 1,
        "packageName": "weather",
        "enclosedBy": {
            "name": "Coordinates",
            "type": "class"
        }
    },
    {
        "name": "Coordinates",
        "qualifiedName": "current_weather.Coordinates.Coordinates",
        "href": "current_weather/Coordinates/Coordinates.html",
        "type": "constructor",
        "overriddenDepth": 0,
        "packageName": "weather",
        "enclosedBy": {
            "name": "Coordinates",
            "type": "class"
        }
    },
    {
        "name": "copyWith",
        "qualifiedName": "current_weather.Coordinates.copyWith",
        "href": "current_weather/Coordinates/copyWith.html",
        "type": "method",
        "overriddenDepth": 0,
        "packageName": "weather",
        "enclosedBy": {
            "name": "Coordinates",
            "type": "class"
        }
    },
    {
        "name": "Coordinates.fromJson",
        "qualifiedName": "current_weather.Coordinates.fromJson",
        "href": "current_weather/Coordinates/Coordinates.fromJson.html",
        "type": "constructor",
        "overriddenDepth": 0,
        "packageName": "weather",
        "enclosedBy": {
            "name": "Coordinates",
            "type": "class"
        }
    },
    {
        "name": "Coordinates.fromMap",
        "qualifiedName": "current_weather.Coordinates.fromMap",
        "href": "current_weather/Coordinates/Coordinates.fromMap.html",
        "type": "constructor",
        "overriddenDepth": 0,
        "packageName": "weather",
        "enclosedBy": {
            "name": "Coordinates",
            "type": "class"
        }
    },
    {
        "name": "hashCode",
        "qualifiedName": "current_weather.Coordinates.hashCode",
        "href": "current_weather/Coordinates/hashCode.html",
        "type": "property",
        "overriddenDepth": 0,
        "packageName": "weather",
        "enclosedBy": {
            "name": "Coordinates",
            "type": "class"
        }
    },
    {
        "name": "latitude",
        "qualifiedName": "current_weather.Coordinates.latitude",
        "href": "current_weather/Coordinates/latitude.html",
        "type": "property",
        "overriddenDepth": 0,
        "packageName": "weather",
        "enclosedBy": {
            "name": "Coordinates",
            "type": "class"
        }
    },
    {
        "name": "longitude",
        "qualifiedName": "current_weather.Coordinates.longitude",
        "href": "current_weather/Coordinates/longitude.html",
        "type": "property",
        "overriddenDepth": 0,
        "packageName": "weather",
        "enclosedBy": {
            "name": "Coordinates",
            "type": "class"
        }
    },
    {
        "name": "toJson",
        "qualifiedName": "current_weather.Coordinates.toJson",
        "href": "current_weather/Coordinates/toJson.html",
        "type": "method",
        "overriddenDepth": 0,
        "packageName": "weather",
        "enclosedBy": {
            "name": "Coordinates",
            "type": "class"
        }
    },
    {
        "name": "toMap",
        "qualifiedName": "current_weather.Coordinates.toMap",
        "href": "current_weather/Coordinates/toMap.html",
        "type": "method",
        "overriddenDepth": 0,
        "packageName": "weather",
        "enclosedBy": {
            "name": "Coordinates",
            "type": "class"
        }
    },
    {
        "name": "toString",
        "qualifiedName": "current_weather.Coordinates.toString",
        "href": "current_weather/Coordinates/toString.html",
        "type": "method",
        "overriddenDepth": 1,
        "packageName": "weather",
        "enclosedBy": {
            "name": "Coordinates",
            "type": "class"
        }
    },
    {
        "name": "CurrentWeather",
        "qualifiedName": "current_weather.CurrentWeather",
        "href": "current_weather/CurrentWeather-class.html",
        "type": "class",
        "overriddenDepth": 0,
        "packageName": "weather",
        "enclosedBy": {
            "name": "current_weather",
            "type": "library"
        }
    },
    {
        "name": "operator ==",
        "qualifiedName": "current_weather.CurrentWeather.==",
        "href": "current_weather/CurrentWeather/operator_equals.html",
        "type": "method",
        "overriddenDepth": 1,
        "packageName": "weather",
        "enclosedBy": {
            "name": "CurrentWeather",
            "type": "class"
        }
    },
    {
        "name": "CurrentWeather",
        "qualifiedName": "current_weather.CurrentWeather.CurrentWeather",
        "href": "current_weather/CurrentWeather/CurrentWeather.html",
        "type": "constructor",
        "overriddenDepth": 0,
        "packageName": "weather",
        "enclosedBy": {
            "name": "CurrentWeather",
            "type": "class"
        }
    },
    {
        "name": "base",
        "qualifiedName": "current_weather.CurrentWeather.base",
        "href": "current_weather/CurrentWeather/base.html",
        "type": "property",
        "overriddenDepth": 0,
        "packageName": "weather",
        "enclosedBy": {
            "name": "CurrentWeather",
            "type": "class"
        }
    },
    {
        "name": "clouds",
        "qualifiedName": "current_weather.CurrentWeather.clouds",
        "href": "current_weather/CurrentWeather/clouds.html",
        "type": "property",
        "overriddenDepth": 0,
        "packageName": "weather",
        "enclosedBy": {
            "name": "CurrentWeather",
            "type": "class"
        }
    },
    {
        "name": "cod",
        "qualifiedName": "current_weather.CurrentWeather.cod",
        "href": "current_weather/CurrentWeather/cod.html",
        "type": "property",
        "overriddenDepth": 0,
        "packageName": "weather",
        "enclosedBy": {
            "name": "CurrentWeather",
            "type": "class"
        }
    },
    {
        "name": "coord",
        "qualifiedName": "current_weather.CurrentWeather.coord",
        "href": "current_weather/CurrentWeather/coord.html",
        "type": "property",
        "overriddenDepth": 0,
        "packageName": "weather",
        "enclosedBy": {
            "name": "CurrentWeather",
            "type": "class"
        }
    },
    {
        "name": "copyWith",
        "qualifiedName": "current_weather.CurrentWeather.copyWith",
        "href": "current_weather/CurrentWeather/copyWith.html",
        "type": "method",
        "overriddenDepth": 0,
        "packageName": "weather",
        "enclosedBy": {
            "name": "CurrentWeather",
            "type": "class"
        }
    },
    {
        "name": "dt",
        "qualifiedName": "current_weather.CurrentWeather.dt",
        "href": "current_weather/CurrentWeather/dt.html",
        "type": "property",
        "overriddenDepth": 0,
        "packageName": "weather",
        "enclosedBy": {
            "name": "CurrentWeather",
            "type": "class"
        }
    },
    {
        "name": "CurrentWeather.fromJson",
        "qualifiedName": "current_weather.CurrentWeather.fromJson",
        "href": "current_weather/CurrentWeather/CurrentWeather.fromJson.html",
        "type": "constructor",
        "overriddenDepth": 0,
        "packageName": "weather",
        "enclosedBy": {
            "name": "CurrentWeather",
            "type": "class"
        }
    },
    {
        "name": "CurrentWeather.fromMap",
        "qualifiedName": "current_weather.CurrentWeather.fromMap",
        "href": "current_weather/CurrentWeather/CurrentWeather.fromMap.html",
        "type": "constructor",
        "overriddenDepth": 0,
        "packageName": "weather",
        "enclosedBy": {
            "name": "CurrentWeather",
            "type": "class"
        }
    },
    {
        "name": "hashCode",
        "qualifiedName": "current_weather.CurrentWeather.hashCode",
        "href": "current_weather/CurrentWeather/hashCode.html",
        "type": "property",
        "overriddenDepth": 0,
        "packageName": "weather",
        "enclosedBy": {
            "name": "CurrentWeather",
            "type": "class"
        }
    },
    {
        "name": "id",
        "qualifiedName": "current_weather.CurrentWeather.id",
        "href": "current_weather/CurrentWeather/id.html",
        "type": "property",
        "overriddenDepth": 0,
        "packageName": "weather",
        "enclosedBy": {
            "name": "CurrentWeather",
            "type": "class"
        }
    },
    {
        "name": "main",
        "qualifiedName": "current_weather.CurrentWeather.main",
        "href": "current_weather/CurrentWeather/main.html",
        "type": "property",
        "overriddenDepth": 0,
        "packageName": "weather",
        "enclosedBy": {
            "name": "CurrentWeather",
            "type": "class"
        }
    },
    {
        "name": "name",
        "qualifiedName": "current_weather.CurrentWeather.name",
        "href": "current_weather/CurrentWeather/name.html",
        "type": "property",
        "overriddenDepth": 0,
        "packageName": "weather",
        "enclosedBy": {
            "name": "CurrentWeather",
            "type": "class"
        }
    },
    {
        "name": "sys",
        "qualifiedName": "current_weather.CurrentWeather.sys",
        "href": "current_weather/CurrentWeather/sys.html",
        "type": "property",
        "overriddenDepth": 0,
        "packageName": "weather",
        "enclosedBy": {
            "name": "CurrentWeather",
            "type": "class"
        }
    },
    {
        "name": "timezone",
        "qualifiedName": "current_weather.CurrentWeather.timezone",
        "href": "current_weather/CurrentWeather/timezone.html",
        "type": "property",
        "overriddenDepth": 0,
        "packageName": "weather",
        "enclosedBy": {
            "name": "CurrentWeather",
            "type": "class"
        }
    },
    {
        "name": "toJson",
        "qualifiedName": "current_weather.CurrentWeather.toJson",
        "href": "current_weather/CurrentWeather/toJson.html",
        "type": "method",
        "overriddenDepth": 0,
        "packageName": "weather",
        "enclosedBy": {
            "name": "CurrentWeather",
            "type": "class"
        }
    },
    {
        "name": "toMap",
        "qualifiedName": "current_weather.CurrentWeather.toMap",
        "href": "current_weather/CurrentWeather/toMap.html",
        "type": "method",
        "overriddenDepth": 0,
        "packageName": "weather",
        "enclosedBy": {
            "name": "CurrentWeather",
            "type": "class"
        }
    },
    {
        "name": "toString",
        "qualifiedName": "current_weather.CurrentWeather.toString",
        "href": "current_weather/CurrentWeather/toString.html",
        "type": "method",
        "overriddenDepth": 1,
        "packageName": "weather",
        "enclosedBy": {
            "name": "CurrentWeather",
            "type": "class"
        }
    },
    {
        "name": "visibility",
        "qualifiedName": "current_weather.CurrentWeather.visibility",
        "href": "current_weather/CurrentWeather/visibility.html",
        "type": "property",
        "overriddenDepth": 0,
        "packageName": "weather",
        "enclosedBy": {
            "name": "CurrentWeather",
            "type": "class"
        }
    },
    {
        "name": "weather",
        "qualifiedName": "current_weather.CurrentWeather.weather",
        "href": "current_weather/CurrentWeather/weather.html",
        "type": "property",
        "overriddenDepth": 0,
        "packageName": "weather",
        "enclosedBy": {
            "name": "CurrentWeather",
            "type": "class"
        }
    },
    {
        "name": "wind",
        "qualifiedName": "current_weather.CurrentWeather.wind",
        "href": "current_weather/CurrentWeather/wind.html",
        "type": "property",
        "overriddenDepth": 0,
        "packageName": "weather",
        "enclosedBy": {
            "name": "CurrentWeather",
            "type": "class"
        }
    },
    {
        "name": "Main",
        "qualifiedName": "current_weather.Main",
        "href": "current_weather/Main-class.html",
        "type": "class",
        "overriddenDepth": 0,
        "packageName": "weather",
        "enclosedBy": {
            "name": "current_weather",
            "type": "library"
        }
    },
    {
        "name": "operator ==",
        "qualifiedName": "current_weather.Main.==",
        "href": "current_weather/Main/operator_equals.html",
        "type": "method",
        "overriddenDepth": 1,
        "packageName": "weather",
        "enclosedBy": {
            "name": "Main",
            "type": "class"
        }
    },
    {
        "name": "Main",
        "qualifiedName": "current_weather.Main.Main",
        "href": "current_weather/Main/Main.html",
        "type": "constructor",
        "overriddenDepth": 0,
        "packageName": "weather",
        "enclosedBy": {
            "name": "Main",
            "type": "class"
        }
    },
    {
        "name": "copyWith",
        "qualifiedName": "current_weather.Main.copyWith",
        "href": "current_weather/Main/copyWith.html",
        "type": "method",
        "overriddenDepth": 0,
        "packageName": "weather",
        "enclosedBy": {
            "name": "Main",
            "type": "class"
        }
    },
    {
        "name": "feelsLike",
        "qualifiedName": "current_weather.Main.feelsLike",
        "href": "current_weather/Main/feelsLike.html",
        "type": "property",
        "overriddenDepth": 0,
        "packageName": "weather",
        "enclosedBy": {
            "name": "Main",
            "type": "class"
        }
    },
    {
        "name": "Main.fromJson",
        "qualifiedName": "current_weather.Main.fromJson",
        "href": "current_weather/Main/Main.fromJson.html",
        "type": "constructor",
        "overriddenDepth": 0,
        "packageName": "weather",
        "enclosedBy": {
            "name": "Main",
            "type": "class"
        }
    },
    {
        "name": "Main.fromMap",
        "qualifiedName": "current_weather.Main.fromMap",
        "href": "current_weather/Main/Main.fromMap.html",
        "type": "constructor",
        "overriddenDepth": 0,
        "packageName": "weather",
        "enclosedBy": {
            "name": "Main",
            "type": "class"
        }
    },
    {
        "name": "hashCode",
        "qualifiedName": "current_weather.Main.hashCode",
        "href": "current_weather/Main/hashCode.html",
        "type": "property",
        "overriddenDepth": 0,
        "packageName": "weather",
        "enclosedBy": {
            "name": "Main",
            "type": "class"
        }
    },
    {
        "name": "humidity",
        "qualifiedName": "current_weather.Main.humidity",
        "href": "current_weather/Main/humidity.html",
        "type": "property",
        "overriddenDepth": 0,
        "packageName": "weather",
        "enclosedBy": {
            "name": "Main",
            "type": "class"
        }
    },
    {
        "name": "pressure",
        "qualifiedName": "current_weather.Main.pressure",
        "href": "current_weather/Main/pressure.html",
        "type": "property",
        "overriddenDepth": 0,
        "packageName": "weather",
        "enclosedBy": {
            "name": "Main",
            "type": "class"
        }
    },
    {
        "name": "temp",
        "qualifiedName": "current_weather.Main.temp",
        "href": "current_weather/Main/temp.html",
        "type": "property",
        "overriddenDepth": 0,
        "packageName": "weather",
        "enclosedBy": {
            "name": "Main",
            "type": "class"
        }
    },
    {
        "name": "tempMax",
        "qualifiedName": "current_weather.Main.tempMax",
        "href": "current_weather/Main/tempMax.html",
        "type": "property",
        "overriddenDepth": 0,
        "packageName": "weather",
        "enclosedBy": {
            "name": "Main",
            "type": "class"
        }
    },
    {
        "name": "tempMin",
        "qualifiedName": "current_weather.Main.tempMin",
        "href": "current_weather/Main/tempMin.html",
        "type": "property",
        "overriddenDepth": 0,
        "packageName": "weather",
        "enclosedBy": {
            "name": "Main",
            "type": "class"
        }
    },
    {
        "name": "toJson",
        "qualifiedName": "current_weather.Main.toJson",
        "href": "current_weather/Main/toJson.html",
        "type": "method",
        "overriddenDepth": 0,
        "packageName": "weather",
        "enclosedBy": {
            "name": "Main",
            "type": "class"
        }
    },
    {
        "name": "toMap",
        "qualifiedName": "current_weather.Main.toMap",
        "href": "current_weather/Main/toMap.html",
        "type": "method",
        "overriddenDepth": 0,
        "packageName": "weather",
        "enclosedBy": {
            "name": "Main",
            "type": "class"
        }
    },
    {
        "name": "toString",
        "qualifiedName": "current_weather.Main.toString",
        "href": "current_weather/Main/toString.html",
        "type": "method",
        "overriddenDepth": 1,
        "packageName": "weather",
        "enclosedBy": {
            "name": "Main",
            "type": "class"
        }
    },
    {
        "name": "System",
        "qualifiedName": "current_weather.System",
        "href": "current_weather/System-class.html",
        "type": "class",
        "overriddenDepth": 0,
        "packageName": "weather",
        "enclosedBy": {
            "name": "current_weather",
            "type": "library"
        }
    },
    {
        "name": "operator ==",
        "qualifiedName": "current_weather.System.==",
        "href": "current_weather/System/operator_equals.html",
        "type": "method",
        "overriddenDepth": 1,
        "packageName": "weather",
        "enclosedBy": {
            "name": "System",
            "type": "class"
        }
    },
    {
        "name": "System",
        "qualifiedName": "current_weather.System.System",
        "href": "current_weather/System/System.html",
        "type": "constructor",
        "overriddenDepth": 0,
        "packageName": "weather",
        "enclosedBy": {
            "name": "System",
            "type": "class"
        }
    },
    {
        "name": "copyWith",
        "qualifiedName": "current_weather.System.copyWith",
        "href": "current_weather/System/copyWith.html",
        "type": "method",
        "overriddenDepth": 0,
        "packageName": "weather",
        "enclosedBy": {
            "name": "System",
            "type": "class"
        }
    },
    {
        "name": "country",
        "qualifiedName": "current_weather.System.country",
        "href": "current_weather/System/country.html",
        "type": "property",
        "overriddenDepth": 0,
        "packageName": "weather",
        "enclosedBy": {
            "name": "System",
            "type": "class"
        }
    },
    {
        "name": "System.fromJson",
        "qualifiedName": "current_weather.System.fromJson",
        "href": "current_weather/System/System.fromJson.html",
        "type": "constructor",
        "overriddenDepth": 0,
        "packageName": "weather",
        "enclosedBy": {
            "name": "System",
            "type": "class"
        }
    },
    {
        "name": "System.fromMap",
        "qualifiedName": "current_weather.System.fromMap",
        "href": "current_weather/System/System.fromMap.html",
        "type": "constructor",
        "overriddenDepth": 0,
        "packageName": "weather",
        "enclosedBy": {
            "name": "System",
            "type": "class"
        }
    },
    {
        "name": "hashCode",
        "qualifiedName": "current_weather.System.hashCode",
        "href": "current_weather/System/hashCode.html",
        "type": "property",
        "overriddenDepth": 0,
        "packageName": "weather",
        "enclosedBy": {
            "name": "System",
            "type": "class"
        }
    },
    {
        "name": "id",
        "qualifiedName": "current_weather.System.id",
        "href": "current_weather/System/id.html",
        "type": "property",
        "overriddenDepth": 0,
        "packageName": "weather",
        "enclosedBy": {
            "name": "System",
            "type": "class"
        }
    },
    {
        "name": "message",
        "qualifiedName": "current_weather.System.message",
        "href": "current_weather/System/message.html",
        "type": "property",
        "overriddenDepth": 0,
        "packageName": "weather",
        "enclosedBy": {
            "name": "System",
            "type": "class"
        }
    },
    {
        "name": "sunrise",
        "qualifiedName": "current_weather.System.sunrise",
        "href": "current_weather/System/sunrise.html",
        "type": "property",
        "overriddenDepth": 0,
        "packageName": "weather",
        "enclosedBy": {
            "name": "System",
            "type": "class"
        }
    },
    {
        "name": "sunset",
        "qualifiedName": "current_weather.System.sunset",
        "href": "current_weather/System/sunset.html",
        "type": "property",
        "overriddenDepth": 0,
        "packageName": "weather",
        "enclosedBy": {
            "name": "System",
            "type": "class"
        }
    },
    {
        "name": "toJson",
        "qualifiedName": "current_weather.System.toJson",
        "href": "current_weather/System/toJson.html",
        "type": "method",
        "overriddenDepth": 0,
        "packageName": "weather",
        "enclosedBy": {
            "name": "System",
            "type": "class"
        }
    },
    {
        "name": "toMap",
        "qualifiedName": "current_weather.System.toMap",
        "href": "current_weather/System/toMap.html",
        "type": "method",
        "overriddenDepth": 0,
        "packageName": "weather",
        "enclosedBy": {
            "name": "System",
            "type": "class"
        }
    },
    {
        "name": "toString",
        "qualifiedName": "current_weather.System.toString",
        "href": "current_weather/System/toString.html",
        "type": "method",
        "overriddenDepth": 1,
        "packageName": "weather",
        "enclosedBy": {
            "name": "System",
            "type": "class"
        }
    },
    {
        "name": "type",
        "qualifiedName": "current_weather.System.type",
        "href": "current_weather/System/type.html",
        "type": "property",
        "overriddenDepth": 0,
        "packageName": "weather",
        "enclosedBy": {
            "name": "System",
            "type": "class"
        }
    },
    {
        "name": "Weather",
        "qualifiedName": "current_weather.Weather",
        "href": "current_weather/Weather-class.html",
        "type": "class",
        "overriddenDepth": 0,
        "packageName": "weather",
        "enclosedBy": {
            "name": "current_weather",
            "type": "library"
        }
    },
    {
        "name": "operator ==",
        "qualifiedName": "current_weather.Weather.==",
        "href": "current_weather/Weather/operator_equals.html",
        "type": "method",
        "overriddenDepth": 1,
        "packageName": "weather",
        "enclosedBy": {
            "name": "Weather",
            "type": "class"
        }
    },
    {
        "name": "Weather",
        "qualifiedName": "current_weather.Weather.Weather",
        "href": "current_weather/Weather/Weather.html",
        "type": "constructor",
        "overriddenDepth": 0,
        "packageName": "weather",
        "enclosedBy": {
            "name": "Weather",
            "type": "class"
        }
    },
    {
        "name": "copyWith",
        "qualifiedName": "current_weather.Weather.copyWith",
        "href": "current_weather/Weather/copyWith.html",
        "type": "method",
        "overriddenDepth": 0,
        "packageName": "weather",
        "enclosedBy": {
            "name": "Weather",
            "type": "class"
        }
    },
    {
        "name": "description",
        "qualifiedName": "current_weather.Weather.description",
        "href": "current_weather/Weather/description.html",
        "type": "property",
        "overriddenDepth": 0,
        "packageName": "weather",
        "enclosedBy": {
            "name": "Weather",
            "type": "class"
        }
    },
    {
        "name": "Weather.fromJson",
        "qualifiedName": "current_weather.Weather.fromJson",
        "href": "current_weather/Weather/Weather.fromJson.html",
        "type": "constructor",
        "overriddenDepth": 0,
        "packageName": "weather",
        "enclosedBy": {
            "name": "Weather",
            "type": "class"
        }
    },
    {
        "name": "Weather.fromMap",
        "qualifiedName": "current_weather.Weather.fromMap",
        "href": "current_weather/Weather/Weather.fromMap.html",
        "type": "constructor",
        "overriddenDepth": 0,
        "packageName": "weather",
        "enclosedBy": {
            "name": "Weather",
            "type": "class"
        }
    },
    {
        "name": "hashCode",
        "qualifiedName": "current_weather.Weather.hashCode",
        "href": "current_weather/Weather/hashCode.html",
        "type": "property",
        "overriddenDepth": 0,
        "packageName": "weather",
        "enclosedBy": {
            "name": "Weather",
            "type": "class"
        }
    },
    {
        "name": "icon",
        "qualifiedName": "current_weather.Weather.icon",
        "href": "current_weather/Weather/icon.html",
        "type": "property",
        "overriddenDepth": 0,
        "packageName": "weather",
        "enclosedBy": {
            "name": "Weather",
            "type": "class"
        }
    },
    {
        "name": "id",
        "qualifiedName": "current_weather.Weather.id",
        "href": "current_weather/Weather/id.html",
        "type": "property",
        "overriddenDepth": 0,
        "packageName": "weather",
        "enclosedBy": {
            "name": "Weather",
            "type": "class"
        }
    },
    {
        "name": "main",
        "qualifiedName": "current_weather.Weather.main",
        "href": "current_weather/Weather/main.html",
        "type": "property",
        "overriddenDepth": 0,
        "packageName": "weather",
        "enclosedBy": {
            "name": "Weather",
            "type": "class"
        }
    },
    {
        "name": "toJson",
        "qualifiedName": "current_weather.Weather.toJson",
        "href": "current_weather/Weather/toJson.html",
        "type": "method",
        "overriddenDepth": 0,
        "packageName": "weather",
        "enclosedBy": {
            "name": "Weather",
            "type": "class"
        }
    },
    {
        "name": "toMap",
        "qualifiedName": "current_weather.Weather.toMap",
        "href": "current_weather/Weather/toMap.html",
        "type": "method",
        "overriddenDepth": 0,
        "packageName": "weather",
        "enclosedBy": {
            "name": "Weather",
            "type": "class"
        }
    },
    {
        "name": "toString",
        "qualifiedName": "current_weather.Weather.toString",
        "href": "current_weather/Weather/toString.html",
        "type": "method",
        "overriddenDepth": 1,
        "packageName": "weather",
        "enclosedBy": {
            "name": "Weather",
            "type": "class"
        }
    },
    {
        "name": "WeatherCondition",
        "qualifiedName": "current_weather.WeatherCondition",
        "href": "current_weather/WeatherCondition-class.html",
        "type": "enum",
        "overriddenDepth": 0,
        "packageName": "weather",
        "enclosedBy": {
            "name": "current_weather",
            "type": "library"
        }
    },
    {
        "name": "toString",
        "qualifiedName": "current_weather.WeatherCondition.toString",
        "href": "current_weather/WeatherCondition/toString.html",
        "type": "method",
        "overriddenDepth": 1,
        "packageName": "weather",
        "enclosedBy": {
            "name": "WeatherCondition",
            "type": "enum"
        }
    },
    {
        "name": "WeatherConditionCodes",
        "qualifiedName": "current_weather.WeatherConditionCodes",
        "href": "current_weather/WeatherConditionCodes-class.html",
        "type": "class",
        "overriddenDepth": 0,
        "packageName": "weather",
        "enclosedBy": {
            "name": "current_weather",
            "type": "library"
        }
    },
    {
        "name": "WeatherConditionCodes",
        "qualifiedName": "current_weather.WeatherConditionCodes.WeatherConditionCodes",
        "href": "current_weather/WeatherConditionCodes/WeatherConditionCodes.html",
        "type": "constructor",
        "overriddenDepth": 0,
        "packageName": "weather",
        "enclosedBy": {
            "name": "WeatherConditionCodes",
            "type": "class"
        }
    },
    {
        "name": "asMap",
        "qualifiedName": "current_weather.WeatherConditionCodes.asMap",
        "href": "current_weather/WeatherConditionCodes/asMap.html",
        "type": "property",
        "overriddenDepth": 0,
        "packageName": "weather",
        "enclosedBy": {
            "name": "WeatherConditionCodes",
            "type": "class"
        }
    },
    {
        "name": "codes",
        "qualifiedName": "current_weather.WeatherConditionCodes.codes",
        "href": "current_weather/WeatherConditionCodes/codes.html",
        "type": "property",
        "overriddenDepth": 0,
        "packageName": "weather",
        "enclosedBy": {
            "name": "WeatherConditionCodes",
            "type": "class"
        }
    },
    {
        "name": "getConditionbyCode",
        "qualifiedName": "current_weather.WeatherConditionCodes.getConditionbyCode",
        "href": "current_weather/WeatherConditionCodes/getConditionbyCode.html",
        "type": "method",
        "overriddenDepth": 0,
        "packageName": "weather",
        "enclosedBy": {
            "name": "WeatherConditionCodes",
            "type": "class"
        }
    },
    {
        "name": "Wind",
        "qualifiedName": "current_weather.Wind",
        "href": "current_weather/Wind-class.html",
        "type": "class",
        "overriddenDepth": 0,
        "packageName": "weather",
        "enclosedBy": {
            "name": "current_weather",
            "type": "library"
        }
    },
    {
        "name": "operator ==",
        "qualifiedName": "current_weather.Wind.==",
        "href": "current_weather/Wind/operator_equals.html",
        "type": "method",
        "overriddenDepth": 1,
        "packageName": "weather",
        "enclosedBy": {
            "name": "Wind",
            "type": "class"
        }
    },
    {
        "name": "Wind",
        "qualifiedName": "current_weather.Wind.Wind",
        "href": "current_weather/Wind/Wind.html",
        "type": "constructor",
        "overriddenDepth": 0,
        "packageName": "weather",
        "enclosedBy": {
            "name": "Wind",
            "type": "class"
        }
    },
    {
        "name": "copyWith",
        "qualifiedName": "current_weather.Wind.copyWith",
        "href": "current_weather/Wind/copyWith.html",
        "type": "method",
        "overriddenDepth": 0,
        "packageName": "weather",
        "enclosedBy": {
            "name": "Wind",
            "type": "class"
        }
    },
    {
        "name": "deg",
        "qualifiedName": "current_weather.Wind.deg",
        "href": "current_weather/Wind/deg.html",
        "type": "property",
        "overriddenDepth": 0,
        "packageName": "weather",
        "enclosedBy": {
            "name": "Wind",
            "type": "class"
        }
    },
    {
        "name": "Wind.fromJson",
        "qualifiedName": "current_weather.Wind.fromJson",
        "href": "current_weather/Wind/Wind.fromJson.html",
        "type": "constructor",
        "overriddenDepth": 0,
        "packageName": "weather",
        "enclosedBy": {
            "name": "Wind",
            "type": "class"
        }
    },
    {
        "name": "Wind.fromMap",
        "qualifiedName": "current_weather.Wind.fromMap",
        "href": "current_weather/Wind/Wind.fromMap.html",
        "type": "constructor",
        "overriddenDepth": 0,
        "packageName": "weather",
        "enclosedBy": {
            "name": "Wind",
            "type": "class"
        }
    },
    {
        "name": "hashCode",
        "qualifiedName": "current_weather.Wind.hashCode",
        "href": "current_weather/Wind/hashCode.html",
        "type": "property",
        "overriddenDepth": 0,
        "packageName": "weather",
        "enclosedBy": {
            "name": "Wind",
            "type": "class"
        }
    },
    {
        "name": "speed",
        "qualifiedName": "current_weather.Wind.speed",
        "href": "current_weather/Wind/speed.html",
        "type": "property",
        "overriddenDepth": 0,
        "packageName": "weather",
        "enclosedBy": {
            "name": "Wind",
            "type": "class"
        }
    },
    {
        "name": "toJson",
        "qualifiedName": "current_weather.Wind.toJson",
        "href": "current_weather/Wind/toJson.html",
        "type": "method",
        "overriddenDepth": 0,
        "packageName": "weather",
        "enclosedBy": {
            "name": "Wind",
            "type": "class"
        }
    },
    {
        "name": "toMap",
        "qualifiedName": "current_weather.Wind.toMap",
        "href": "current_weather/Wind/toMap.html",
        "type": "method",
        "overriddenDepth": 0,
        "packageName": "weather",
        "enclosedBy": {
            "name": "Wind",
            "type": "class"
        }
    },
    {
        "name": "toString",
        "qualifiedName": "current_weather.Wind.toString",
        "href": "current_weather/Wind/toString.html",
        "type": "method",
        "overriddenDepth": 1,
        "packageName": "weather",
        "enclosedBy": {
            "name": "Wind",
            "type": "class"
        }
    },
    {
        "name": "byCityId",
        "qualifiedName": "current_weather.byCityId",
        "href": "current_weather/byCityId.html",
        "type": "function",
        "overriddenDepth": 0,
        "packageName": "weather",
        "enclosedBy": {
            "name": "current_weather",
            "type": "library"
        }
    },
    {
        "name": "byCityName",
        "qualifiedName": "current_weather.byCityName",
        "href": "current_weather/byCityName.html",
        "type": "function",
        "overriddenDepth": 0,
        "packageName": "weather",
        "enclosedBy": {
            "name": "current_weather",
            "type": "library"
        }
    },
    {
        "name": "byCoordinates",
        "qualifiedName": "current_weather.byCoordinates",
        "href": "current_weather/byCoordinates.html",
        "type": "function",
        "overriddenDepth": 0,
        "packageName": "weather",
        "enclosedBy": {
            "name": "current_weather",
            "type": "library"
        }
    },
    {
        "name": "byZipCode",
        "qualifiedName": "current_weather.byZipCode",
        "href": "current_weather/byZipCode.html",
        "type": "function",
        "overriddenDepth": 0,
        "packageName": "weather",
        "enclosedBy": {
            "name": "current_weather",
            "type": "library"
        }
    },
    {
        "name": "hourly_forecast",
        "qualifiedName": "hourly_forecast",
        "href": "hourly_forecast/hourly_forecast-library.html",
        "type": "library",
        "overriddenDepth": 0,
        "packageName": "weather"
    },
    {
        "name": "currentWeatherBaseUrl",
        "qualifiedName": "hourly_forecast.currentWeatherBaseUrl",
        "href": "hourly_forecast/currentWeatherBaseUrl-constant.html",
        "type": "top-level constant",
        "overriddenDepth": 0,
        "packageName": "weather",
        "enclosedBy": {
            "name": "hourly_forecast",
            "type": "library"
        }
    }
]